.gitignore
.gitlab-ci.yml
CHANGELOG.md
CMakeLists.txt
COPYING
INSTALL
LICENSE.md
README.md
config.h.cmake
dune-grid.pc.in
dune.module
pyproject.toml
setup.py
LICENSES/LGPL-3.0-or-later.txt
LICENSES/LicenseRef-GPL-2.0-only-with-DUNE-exception.txt
cmake/modules/AddAlbertaFlags.cmake
cmake/modules/CMakeLists.txt
cmake/modules/DuneGridMacros.cmake
cmake/modules/FindAlberta.cmake
cmake/modules/GridType.cmake
doc/CMakeLists.txt
doc/doxygen/CMakeLists.txt
doc/doxygen/Doxydep
doc/doxygen/Doxylocal
doc/doxygen/mainpage.txt
doc/doxygen/modules.txt
doc/grids/CMakeLists.txt
doc/grids/amc/CMakeLists.txt
doc/grids/amc/grid-1-1.amc
doc/grids/amc/grid-1-2.amc
doc/grids/amc/grid-1-3.amc
doc/grids/amc/grid-2-2.amc
doc/grids/amc/grid-2-3.amc
doc/grids/amc/grid-2-4.amc
doc/grids/amc/grid-3-3.amc
doc/grids/amc/macro.amc
doc/grids/amc/periodic-torus.amc
doc/grids/dgf/CMakeLists.txt
doc/grids/dgf/basicunitcube-2d.dgf
doc/grids/dgf/cube-2.dgf
doc/grids/dgf/cube-testgrid-2-2.dgf
doc/grids/dgf/cube-testgrid-2-3.dgf
doc/grids/dgf/cube_grid.dgf
doc/grids/dgf/distorted-cube-3.dgf
doc/grids/dgf/example-projection.dgf
doc/grids/dgf/examplegrid10.dgf
doc/grids/dgf/examplegrid10a.dgf
doc/grids/dgf/examplegrid10b.dgf
doc/grids/dgf/examplegrid11.dgf
doc/grids/dgf/examplegrid12.dgf
doc/grids/dgf/examplegrid1c.dgf
doc/grids/dgf/examplegrid1gen.dgf
doc/grids/dgf/examplegrid1s.dgf
doc/grids/dgf/examplegrid2a.dgf
doc/grids/dgf/examplegrid2b.dgf
doc/grids/dgf/examplegrid2c.dgf
doc/grids/dgf/examplegrid2d.dgf
doc/grids/dgf/examplegrid2e.dgf
doc/grids/dgf/examplegrid5.dgf
doc/grids/dgf/examplegrid6.dgf
doc/grids/dgf/examplegrid7.dgf
doc/grids/dgf/examplegrid9.dgf
doc/grids/dgf/grid2Y.dgf
doc/grids/dgf/grid3A.dgf
doc/grids/dgf/grid3Y.dgf
doc/grids/dgf/helix-deprecated.dgf
doc/grids/dgf/helix.dgf
doc/grids/dgf/octahedron.dgf
doc/grids/dgf/simplex-testgrid-1-1.dgf
doc/grids/dgf/simplex-testgrid-1-2.dgf
doc/grids/dgf/simplex-testgrid-1-3.dgf
doc/grids/dgf/simplex-testgrid-2-2.dgf
python/dune_grid.egg-info/PKG-INFO
python/dune_grid.egg-info/SOURCES.txt
python/dune_grid.egg-info/dependency_links.txt
python/dune_grid.egg-info/requires.txt
python/dune_grid.egg-info/top_level.txt
