Metadata-Version: 2.1
Name: dune-grid
Version: 2.11.0.1
Summary: module providing main interfaces for setting and traversing grids
Home-page: https://gitlab.dune-project.org/core/dune-grid
Author: The Dune Core developers
Author-email: dune-devel@lists.dune-project.org
Classifier: Programming Language :: C++
Classifier: Programming Language :: Python :: 3
Classifier: License :: OSI Approved :: GNU General Public License (GPL)
Requires-Python: >=3.4
License-File: LICENSE.md
License-File: COPYING
